django_phrase-2.1.2.dist-info/licenses/LICENSE
phrase/__init__.py
phrase/compat.py
phrase/nodes.py
phrase/settings.py
phrase/utils.py
phrase/templatetags/__init__.py
phrase/templatetags/phrase_i18n.py
django_phrase-2.1.2.dist-info/METADATA
django_phrase-2.1.2.dist-info/WHEEL
django_phrase-2.1.2.dist-info/top_level.txt
django_phrase-2.1.2.dist-info/RECORD
