Metadata-Version: 2.4
Name: django-phrase
Version: 2.1.2
Summary: Connect your Django apps to Phrase with the powerful in-context-translation solution.
Author-email: Phrase <info@phrase.com>
Project-URL: Homepage, https://github.com/phrase/django-phrase
Project-URL: Bug Tracker, https://github.com/phrase/django-phrase/issues
Classifier: Environment :: Web Environment
Classifier: Framework :: Django
Classifier: Intended Audience :: Developers
Classifier: License :: OSI Approved :: MIT License
Classifier: Operating System :: OS Independent
Classifier: Programming Language :: Python
Classifier: Topic :: Software Development :: Libraries :: Python Modules
Classifier: Topic :: Software Development :: Internationalization
Classifier: Topic :: Software Development :: Localization
Requires-Python: >=3.6
License-File: LICENSE
Requires-Dist: django
Requires-Dist: six==1.16.0
Dynamic: license-file
